mentalHealth/TfIdf_Vectorizer.pk
mentalHealth/__init__.py
mentalHealth/mentalHealth.py
mentalHealth/server.py
mentalHealth/svc_linear.pk
mentalHealth-1.14.data/scripts/mentalHealth
mentalHealth-1.14.dist-info/METADATA
mentalHealth-1.14.dist-info/WHEEL
mentalHealth-1.14.dist-info/top_level.txt
mentalHealth-1.14.dist-info/RECORD
